omop_pydantic/__init__.py
omop_pydantic/base.py
omop_pydantic/models/__init__.py
omop_pydantic/models/attribute_definition.py
omop_pydantic/models/care_site.py
omop_pydantic/models/cdm_source.py
omop_pydantic/models/cohort_definition.py
omop_pydantic/models/concept.py
omop_pydantic/models/concept_ancestor.py
omop_pydantic/models/concept_class.py
omop_pydantic/models/concept_relationship.py
omop_pydantic/models/concept_synonym.py
omop_pydantic/models/condition_era.py
omop_pydantic/models/condition_occurrence.py
omop_pydantic/models/cost.py
omop_pydantic/models/death.py
omop_pydantic/models/device_exposure.py
omop_pydantic/models/domain.py
omop_pydantic/models/dose_era.py
omop_pydantic/models/drug_era.py
omop_pydantic/models/drug_exposure.py
omop_pydantic/models/drug_strength.py
omop_pydantic/models/episode.py
omop_pydantic/models/episode_event.py
omop_pydantic/models/fact_relationship.py
omop_pydantic/models/location.py
omop_pydantic/models/measurement.py
omop_pydantic/models/metadata.py
omop_pydantic/models/note.py
omop_pydantic/models/note_nlp.py
omop_pydantic/models/observation.py
omop_pydantic/models/observation_period.py
omop_pydantic/models/payer_plan_period.py
omop_pydantic/models/person.py
omop_pydantic/models/procedure_occurrence.py
omop_pydantic/models/provider.py
omop_pydantic/models/relationship.py
omop_pydantic/models/source_to_concept_map.py
omop_pydantic/models/specimen.py
omop_pydantic/models/visit_detail.py
omop_pydantic/models/visit_occurrence.py
omop_pydantic/models/vocabulary.py
omop_pydantic-0.1.0.dist-info/METADATA
omop_pydantic-0.1.0.dist-info/WHEEL
omop_pydantic-0.1.0.dist-info/licenses/LICENSE
omop_pydantic-0.1.0.dist-info/RECORD
