Metadata-Version: 2.4
Name: omop-pydantic
Version: 0.1.0
Summary: Simple Pydantic models for OMOP CDM
License-File: LICENSE
Requires-Python: >=3.12
Requires-Dist: hypothesis>=6.131.30
Requires-Dist: pydantic>=2.11.5
Requires-Dist: pytest-lazy-fixture>=0.6.3
